envmaster/__init__.py
envmaster/env.py
envmaster-1.0.0.dist-info/METADATA
envmaster-1.0.0.dist-info/WHEEL
envmaster-1.0.0.dist-info/RECORD
